jamboree/__init__.py
jamboree/base/__init__.py
jamboree/base/core.py
jamboree/base/handler.py
jamboree/base/refactor.py
jamboree/base/old/__init__.py
jamboree/base/old/flat_jam.py
jamboree/base/old/refactor.py
jamboree/base/processors/__init__.py
jamboree/base/processors/event.py
jamboree/base/processors/files.py
jamboree/base/processors/legacy.py
jamboree/base/processors/main.py
jamboree/base/processors/search.py
jamboree/base/processors/abstracts/__init__.py
jamboree/base/processors/abstracts/event.py
jamboree/base/processors/abstracts/files.py
jamboree/base/processors/abstracts/legacy.py
jamboree/base/processors/abstracts/main.py
jamboree/base/processors/abstracts/search.py
jamboree/handlers/__init__.py
jamboree/handlers/base.py
jamboree/handlers/abstracted/__init__.py
jamboree/handlers/abstracted/features.py
jamboree/handlers/abstracted/datasets/__init__.py
jamboree/handlers/abstracted/datasets/economic.py
jamboree/handlers/abstracted/datasets/orderbook.py
jamboree/handlers/abstracted/datasets/price.py
jamboree/handlers/abstracted/models/__init__.py
jamboree/handlers/abstracted/models/cremee.py
jamboree/handlers/abstracted/models/flow.py
jamboree/handlers/abstracted/models/learn.py
jamboree/handlers/abstracted/models/ptorch.py
jamboree/handlers/abstracted/search/__init__.py
jamboree/handlers/abstracted/search/meta.py
jamboree/handlers/abstracted/search/updated.py
jamboree/handlers/complex/__init__.py
jamboree/handlers/complex/meta.py
jamboree/handlers/complex/metric.py
jamboree/handlers/complex/model.py
jamboree/handlers/complex/backtestable/__init__.py
jamboree/handlers/complex/backtestable/db.py
jamboree/handlers/complex/backtestable/files.py
jamboree/handlers/complex/backtestable/default/__init__.py
jamboree/handlers/complex/backtestable/default/db.py
jamboree/handlers/complex/backtestable/default/files.py
jamboree/handlers/complex/engines/__init__.py
jamboree/handlers/complex/engines/files.py
jamboree/handlers/default/__init__.py
jamboree-0.9.7.dist-info/METADATA
jamboree-0.9.7.dist-info/WHEEL
jamboree-0.9.7.dist-info/top_level.txt
jamboree-0.9.7.dist-info/RECORD
