Metadata-Version: 2.1
Name: jamboree
Version: 0.9.7
Summary: A multi-layer event sourcing and general data library. SQL, Search, Event Sourcing, and File/Model storage combined into one.
Home-page: UNKNOWN
Author: Kevin Hill
Author-email: kah.kevin.hill@gmail.com
License: UNKNOWN
Platform: UNKNOWN
Classifier: Programming Language :: Python :: 3
Classifier: License :: OSI Approved :: MIT License
Classifier: Operating System :: OS Independent
Requires-Dist: numpy
Requires-Dist: scipy
Requires-Dist: maya
Requires-Dist: pandas-datareader
Requires-Dist: json-tricks
Requires-Dist: ujson
Requires-Dist: gym
Requires-Dist: orjson
Requires-Dist: pebble
Requires-Dist: cytoolz
Requires-Dist: loguru
Requires-Dist: redisearch
Requires-Dist: lz4
Requires-Dist: anycache
Requires-Dist: hiredis
Requires-Dist: eliot
Requires-Dist: eliot-tree
Requires-Dist: matplotlib
Requires-Dist: pandas
Requires-Dist: sklearn
Requires-Dist: crayons
Requires-Dist: creme
Requires-Dist: pydantic
Requires-Dist: yfinance
Requires-Dist: version-query
Requires-Dist: cerberus
Requires-Dist: addict
